dpd_lib/__init__.py
dpd_lib/config.py
dpd_lib/models.py
dpd_lib/plot.py
dpd_lib/utils.py
dpd_lib/client/__init__.py
dpd_lib/client/exceptions.py
dpd_lib/client/influx.py
dpd_lib/client/test.py
dpd_lib-0.5.14.dist-info/METADATA
dpd_lib-0.5.14.dist-info/WHEEL
dpd_lib-0.5.14.dist-info/top_level.txt
dpd_lib-0.5.14.dist-info/RECORD
