Metadata-Version: 2.2
Name: dpd_lib
Version: 0.5.14
Summary: A package for interacting with the USGS influx db
Author-email: Noah Harper <nharper@usgs.gov>
Project-URL: Homepage, https://code.usgs.gov/cvo-realtime-seismic/derived-project-database
Project-URL: Issues, https://code.usgs.gov/cvo-realtime-seismic/derived-project-database/-/issues
Keywords: infrasound,seismic,usgs,volcanos
Classifier: Programming Language :: Python :: 3.10
Classifier: Operating System :: OS Independent
Requires-Python: >=3.10
Requires-Dist: numpy
Requires-Dist: pandas
Requires-Dist: obspy
Requires-Dist: influxdb-client
Requires-Dist: fastapi
Requires-Dist: pydantic
Requires-Dist: pydantic_settings
Requires-Dist: uvicorn
Requires-Dist: datetime
Requires-Dist: loguru
Requires-Dist: httpx
Requires-Dist: plotly
